hanieh_release/__init__.py
hanieh_release/kafka.py
hanieh_release/monitoring.py
hanieh_release/scheduler.py
hanieh_release/utils.py
hanieh_release-0.1.0.dist-info/LICENSE
hanieh_release-0.1.0.dist-info/WHEEL
hanieh_release-0.1.0.dist-info/METADATA
hanieh_release-0.1.0.dist-info/RECORD
